__init__.py
uuid_v9.py
uuid_v9-0.1.1.dist-info/LICENSE
uuid_v9-0.1.1.dist-info/METADATA
uuid_v9-0.1.1.dist-info/WHEEL
uuid_v9-0.1.1.dist-info/top_level.txt
uuid_v9-0.1.1.dist-info/RECORD
