Metadata-Version: 2.1
Name: uuid-v9
Version: 0.1.1
Summary: Fast, lightweight, and dependency-free implementation of the UUID version 9 proposal for Python.
Author: JHunt
Author-email: hello@jhunt.dev
Platform: any
Classifier: Intended Audience :: Developers
Classifier: Topic :: Software Development :: Libraries
Classifier: Programming Language :: Python :: 3
Classifier: License :: OSI Approved :: MIT License
Classifier: Operating System :: OS Independent
Requires-Python: >=3.8
License-File: LICENSE
